clyptq/__init__.py
clyptq/analytics/__init__.py
clyptq/analytics/factors/__init__.py
clyptq/analytics/factors/analyzer.py
clyptq/analytics/factors/signal_quality.py
clyptq/analytics/factors/turnover.py
clyptq/analytics/performance/__init__.py
clyptq/analytics/performance/attribution.py
clyptq/analytics/performance/drawdown.py
clyptq/analytics/performance/metrics.py
clyptq/analytics/performance/rolling.py
clyptq/analytics/reporting/__init__.py
clyptq/analytics/reporting/data_explorer.py
clyptq/analytics/reporting/report.py
clyptq/analytics/reporting/visualizations.py
clyptq/analytics/risk/__init__.py
clyptq/analytics/risk/monte_carlo.py
clyptq/core/__init__.py
clyptq/core/base.py
clyptq/core/types.py
clyptq/data/__init__.py
clyptq/data/validation.py
clyptq/data/live/__init__.py
clyptq/data/live/buffer.py
clyptq/data/live/view.py
clyptq/data/loaders/__init__.py
clyptq/data/loaders/ccxt.py
clyptq/data/stores/__init__.py
clyptq/data/stores/live_store.py
clyptq/data/stores/mtf_store.py
clyptq/data/stores/store.py
clyptq/data/streams/__init__.py
clyptq/data/streams/base.py
clyptq/data/streams/ccxt_stream.py
clyptq/infra/__init__.py
clyptq/infra/cli/main.py
clyptq/infra/cli/commands/__init__.py
clyptq/infra/cli/commands/backtest.py
clyptq/infra/cli/commands/data.py
clyptq/infra/cli/commands/live.py
clyptq/infra/cli/commands/paper.py
clyptq/infra/health/__init__.py
clyptq/infra/health/checker.py
clyptq/infra/security/__init__.py
clyptq/infra/security/secrets.py
clyptq/infra/utils/__init__.py
clyptq/infra/utils/logging.py
clyptq/infra/utils/rate_limiter.py
clyptq/infra/utils/shutdown.py
clyptq/trading/__init__.py
clyptq/trading/engine/__init__.py
clyptq/trading/engine/backtest.py
clyptq/trading/engine/live.py
clyptq/trading/execution/__init__.py
clyptq/trading/execution/backtest.py
clyptq/trading/execution/live.py
clyptq/trading/execution/order_tracker.py
clyptq/trading/execution/position_sync.py
clyptq/trading/factors/__init__.py
clyptq/trading/factors/parallel.py
clyptq-1.0.0.dist-info/METADATA
clyptq-1.0.0.dist-info/WHEEL
clyptq-1.0.0.dist-info/entry_points.txt
clyptq-1.0.0.dist-info/top_level.txt
clyptq-1.0.0.dist-info/RECORD
