Metadata-Version: 2.4
Name: clyptq
Version: 1.0.0
Summary: Quantitative cryptocurrency trading engine
Author-email: Jaden - Clypt <jaden@clypt.ai>
Classifier: Development Status :: 5 - Production/Stable
Classifier: Intended Audience :: Financial and Insurance Industry
Classifier: License :: OSI Approved :: MIT License
Classifier: Programming Language :: Python :: 3.10
Classifier: Programming Language :: Python :: 3.11
Classifier: Programming Language :: Python :: 3.12
Classifier: Programming Language :: Python :: 3.13
Classifier: Topic :: Office/Business :: Financial :: Investment
Requires-Python: >=3.10
Requires-Dist: numpy>=1.24.0
Requires-Dist: pandas>=2.0.0
Requires-Dist: ccxt>=4.0.0
Requires-Dist: python-dotenv>=1.0.0
Requires-Dist: matplotlib>=3.7.0
Requires-Dist: scipy>=1.11.0
Requires-Dist: scikit-learn>=1.3.0
Provides-Extra: dev
Requires-Dist: pytest>=7.4.0; extra == "dev"
Requires-Dist: pytest-cov>=4.1.0; extra == "dev"
Requires-Dist: pytest-asyncio>=0.21.0; extra == "dev"
Requires-Dist: mypy>=1.5.0; extra == "dev"
Requires-Dist: black>=23.7.0; extra == "dev"
Requires-Dist: flake8>=6.1.0; extra == "dev"
Requires-Dist: isort>=5.12.0; extra == "dev"
